[
  {
    "full_name": "HelloYeew/mamizu-api",
    "stargazers_count": 1,
    "open_issues_count": 5,
    "forks_count": 0
  },
  {
    "full_name": "impira/docquery",
    "stargazers_count": 1223,
    "open_issues_count": 17,
    "forks_count": 52
  },
  {
    "full_name": "bcoe/c8",
    "stargazers_count": 1590,
    "open_issues_count": 84,
    "forks_count": 72
  },
  {
    "full_name": "andriisoldatenko/awesome-performance-testing",
    "stargazers_count": 129,
    "open_issues_count": 2,
    "forks_count": 22
  },
  {
    "full_name": "enaqx/awesome-pentest",
    "stargazers_count": 17453,
    "open_issues_count": 37,
    "forks_count": 4123
  },
  {
    "full_name": "AlirieGray/da-state-manager-backend",
    "stargazers_count": 1,
    "open_issues_count": 3,
    "forks_count": 0
  },
  {
    "full_name": "open-sauced/api.opensauced.pizza",
    "stargazers_count": 13,
    "open_issues_count": 19,
    "forks_count": 6
  },
  {
    "full_name": "bdougie/awesome-black-developers",
    "stargazers_count": 203,
    "open_issues_count": 1,
    "forks_count": 21
  },
  {
    "full_name": "techfort/LokiJS",
    "stargazers_count": 6358,
    "open_issues_count": 21,
    "forks_count": 487
  },
  {
    "full_name": "isaiahmoran/express-example",
    "stargazers_count": 1,
    "open_issues_count": 1,
    "forks_count": 1
  },
  {
    "full_name": "GreenField-Org/ultracrewapi",
    "stargazers_count": 3,
    "open_issues_count": 5,
    "forks_count": 0
  },
  {
    "full_name": "JeffBeltran/faker.js-docs",
    "stargazers_count": 25,
    "open_issues_count": 0,
    "forks_count": 4
  },
  {
    "full_name": "codex-team/editor.js",
    "stargazers_count": 21071,
    "open_issues_count": 466,
    "forks_count": 1642
  },
  {
    "full_name": "kuchin/awesome-cto",
    "stargazers_count": 18508,
    "open_issues_count": 0,
    "forks_count": 1004
  },
  {
    "full_name": "deckgo/deckdeckgo",
    "stargazers_count": 1534,
    "open_issues_count": 103,
    "forks_count": 163
  },
  {
    "full_name": "npm/hosted-git-info",
    "stargazers_count": 203,
    "open_issues_count": 5,
    "forks_count": 100
  },
  {
    "full_name": "karanpratapsingh/system-design",
    "stargazers_count": 13971,
    "open_issues_count": 2,
    "forks_count": 1129
  },
  {
    "full_name": "drawrowfly/instagram-scraper",
    "stargazers_count": 373,
    "open_issues_count": 32,
    "forks_count": 47
  },
  {
    "full_name": "rkusa/pdfjs",
    "stargazers_count": 607,
    "open_issues_count": 63,
    "forks_count": 132
  },
  {
    "full_name": "redwoodjs/redwood",
    "stargazers_count": 15449,
    "open_issues_count": 437,
    "forks_count": 835
  },
  {
    "full_name": "squalrus/gdd",
    "stargazers_count": 4,
    "open_issues_count": 0,
    "forks_count": 5
  },
  {
    "full_name": "praparn/github-action-any-cloud-env",
    "stargazers_count": 2,
    "open_issues_count": 0,
    "forks_count": 1
  },
  {
    "full_name": "restqa/restqa",
    "stargazers_count": 55,
    "open_issues_count": 15,
    "forks_count": 8
  },
  {
    "full_name": "restqa/cucumber-export",
    "stargazers_count": 12,
    "open_issues_count": 16,
    "forks_count": 0
  },
  {
    "full_name": "mrak/stubby4node",
    "stargazers_count": 258,
    "open_issues_count": 24,
    "forks_count": 61
  },
  {
    "full_name": "erxes/erxes",
    "stargazers_count": 2639,
    "open_issues_count": 547,
    "forks_count": 974
  },
  {
    "full_name": "tony-go/rqapi",
    "stargazers_count": 1,
    "open_issues_count": 0,
    "forks_count": 0
  },
  {
    "full_name": "nastyox/Repo-Roster",
    "stargazers_count": 229,
    "open_issues_count": 2,
    "forks_count": 21
  },
  {
    "full_name": "Codeception/Codeception",
    "stargazers_count": 4630,
    "open_issues_count": 125,
    "forks_count": 1313
  },
  {
    "full_name": "jsumners/alfred-emoji",
    "stargazers_count": 662,
    "open_issues_count": 13,
    "forks_count": 30
  }
]